{
  "type": "Feature",
  "geometry": {
    "type": "Point",
    "coordinates": [
      34.842431600000054,
      38.645974,
      1107.214111328125
    ]
  },
  "properties": {
    "name": "Cappadocia",
    "countryCode": "TR",
    "tags": [
      "Nature",
      "Rock",
      "Cliffs",
      "Town",
      "Mountains",
      "UNESCO World Heritage Site"
    ],
    "image": [
      "cappadocia-01.jpg",
      "cappadocia-02.jpg",
      "cappadocia-03.jpg",
      "cappadocia-04.jpg"
    ],
    "link": "https://en.wikipedia.org/wiki/Cappadocia",
    "contributedBy": "Sarene",
    "description": "In a spectacular landscape, entirely sculpted by erosion, the Göreme valley and its surroundings contain rock-hewn sanctuaries that provide unique evidence of Byzantine art in the post-Iconoclastic period. The density of its rock-hewn dwellings, churches, troglodyte villages and subterranean cities within the rock formations make it one of the world's most striking and largest cave-dwelling complexes. Though interesting from a geological and ethnological point of view, the incomparable beauty of the decor of the Christian sanctuaries makes Cappadocia one of the leading examples of the post-iconoclastic Byzantine art period, some dating back to the 4th century. Residents live in homes that are carved into the landscape. Cappadocia has a unique landscape that you will have never witnessed before in your lifetime. This makes it one of the most popular spots in the world to go up in a Hot Air Balloon."
  }
}
